selectml/__init__.py
selectml/models.py
selectml/pipeline.py
selectml/preprocessing.py
selectml-0.1.1.dist-info/LICENSE
selectml-0.1.1.dist-info/METADATA
selectml-0.1.1.dist-info/WHEEL
selectml-0.1.1.dist-info/top_level.txt
selectml-0.1.1.dist-info/RECORD
