Metadata-Version: 2.2
Name: selectml
Version: 0.1.1
Summary: A streamlined pipeline for model selection, data preprocessing, training, and evaluation
Home-page: https://github.com/CornelliusYW/selectml
Author: Cornellius Yudha Wijaya
Author-email: cornelliusyudhawijaya@gmail.com
Classifier: Programming Language :: Python :: 3
Classifier: License :: OSI Approved :: MIT License
Requires-Python: >=3.6
License-File: LICENSE
Requires-Dist: pandas
Requires-Dist: numpy
Requires-Dist: scikit-learn
Dynamic: author
Dynamic: author-email
Dynamic: classifier
Dynamic: description
Dynamic: description-content-type
Dynamic: home-page
Dynamic: requires-dist
Dynamic: requires-python
Dynamic: summary
